abstractcp/__init__.py
abstractcp/py.typed
abstractcp-1.0.0.dist-info/LICENSE
abstractcp-1.0.0.dist-info/METADATA
abstractcp-1.0.0.dist-info/WHEEL
abstractcp-1.0.0.dist-info/top_level.txt
abstractcp-1.0.0.dist-info/RECORD
