Metadata-Version: 2.1
Name: abstractcp
Version: 1.0.0
Summary: Create abstract class variables
Home-page: https://github.com/reinhrst/abstractcp
Author: Claude El
Author-email: abstractcp@claude.nl
Classifier: Programming Language :: Python :: 3
Classifier: License :: OSI Approved :: MIT License
Classifier: Operating System :: OS Independent
Requires-Python: >=3.8
License-File: LICENSE
